kyaml/__init__.py
kyaml/cli.py
kyaml/split.py
kyaml-0.1.3.dist-info/METADATA
kyaml-0.1.3.dist-info/WHEEL
kyaml-0.1.3.dist-info/entry_points.txt
kyaml-0.1.3.dist-info/top_level.txt
kyaml-0.1.3.dist-info/RECORD
